{
  "timestamp": "20250711_151215",
  "files": [
    {
      "original_path": "customer_section_v2.py",
      "backup_path": "backup_customer_files_20250711_151215\\customer_section_v2.py",
      "archive_path": "archive\\legacy_versions\\customer_section_v2.py",
      "category": "legacy_versions",
      "size": 808
    },
    {
      "original_path": "welcome_screen_components/customer_section.py",
      "backup_path": "backup_customer_files_20250711_151215\\welcome_screen_components\\customer_section.py",
      "archive_path": "archive\\legacy_versions\\customer_section.py",
      "category": "legacy_versions",
      "size": 14353
    },
    {
      "original_path": "welcome_screen_components/customer_section_v2.py",
      "backup_path": "backup_customer_files_20250711_151215\\welcome_screen_components\\customer_section_v2.py",
      "archive_path": "archive\\legacy_versions\\customer_section_v2.py",
      "category": "legacy_versions",
      "size": 25840
    },
    {
      "original_path": "welcome_screen_components/customer_section_with_calendar.py",
      "backup_path": "backup_customer_files_20250711_151215\\welcome_screen_components\\customer_section_with_calendar.py",
      "archive_path": "archive\\legacy_versions\\customer_section_with_calendar.py",
      "category": "legacy_versions",
      "size": 52679
    },
    {
      "original_path": "customer_management_integration.py",
      "backup_path": "backup_customer_files_20250711_151215\\customer_management_integration.py",
      "archive_path": "archive\\integration_files\\customer_management_integration.py",
      "category": "integration_files",
      "size": 26339
    },
    {
      "original_path": "customer_management_final_integration.py",
      "backup_path": "backup_customer_files_20250711_151215\\customer_management_final_integration.py",
      "archive_path": "archive\\integration_files\\customer_management_final_integration.py",
      "category": "integration_files",
      "size": 20526
    }
  ]
}