{
  "created_icons": 14,
  "total_icons": 14,
  "icon_size": [
    32,
    32
  ],
  "format": "PNG with RGBA transparency",
  "created_files": [
    "check-mark.png",
    "close.png",
    "doc-file.png",
    "file.png",
    "home.png",
    "idea.png",
    "image-file.png",
    "info.png",
    "pdf-file.png",
    "play.png",
    "restart.png",
    "settings.png",
    "toolbox.png",
    "txt-file.png"
  ],
  "errors": [],
  "descriptions": {
    "check-mark.png": "Checkmark for success states",
    "close.png": "X symbol for close/cancel",
    "doc-file.png": "Document file icon",
    "file.png": "Generic file icon",
    "home.png": "Home/house icon",
    "idea.png": "Lightbulb for ideas",
    "image-file.png": "Image file icon",
    "info.png": "Information icon",
    "pdf-file.png": "PDF file icon",
    "play.png": "Play button triangle",
    "restart.png": "Refresh/restart icon",
    "settings.png": "Settings gear icon",
    "toolbox.png": "Toolbox icon",
    "txt-file.png": "Text file icon"
  }
}